{
  "when": "2025-08-27T10:26:20.839796-05:00",
  "timezone": "America/Chicago",
  "sources": [
    {
      "name": "Vilas County (Modern Tribe)",
      "url": "https://vilaswi.com/events/?eventDisplay=list",
      "parsed": 0,
      "samples": []
    },
    {
      "name": "Boulder Junction (Modern Tribe)",
      "url": "https://boulderjct.org/events/?eventDisplay=list",
      "parsed": 0,
      "samples": []
    },
    {
      "name": "Oneida County \u2013 Festivals & Events (Modern Tribe)",
      "url": "https://oneidacountywi.com/festivals-events/?eventDisplay=list",
      "parsed": 0,
      "samples": []
    },
    {
      "name": "Eagle River Chamber (Modern Tribe)",
      "url": "https://eagleriver.org/events/?eventDisplay=list",
      "parsed": 0,
      "samples": []
    },
    {
      "name": "Rhinelander Chamber (GrowthZone)",
      "url": "https://business.rhinelanderchamber.com/events/calendar",
      "parsed": 0,
      "samples": []
    },
    {
      "name": "St. Germain Chamber (Modern Tribe)",
      "url": "https://st-germain.com/events-calendar/?eventDisplay=list",
      "parsed": 0,
      "samples": []
    },
    {
      "name": "Minocqua Area Chamber (Modern Tribe)",
      "url": "https://www.minocqua.org/events/?eventDisplay=list",
      "parsed": 0,
      "samples": []
    },
    {
      "name": "Town of Arbor Vitae (Municipal Calendar)",
      "url": "https://www.townofarborvitae.org/calendar/",
      "parsed": 0,
      "samples": []
    },
    {
      "name": "Sayner\u2013Star Lake\u2013Cloverland Chamber (Modern Tribe)",
      "url": "https://sayner-starlake-cloverland.org/events/",
      "parsed": 11,
      "samples": [
        {
          "title": "Plum Ski-ters Water Ski Show",
          "url": "https://sayner-starlake-cloverland.org/event/plum-ski-ters-water-ski-show-2/2025-08-27/",
          "source": "Sayner\u2013Star Lake\u2013Cloverland Chamber (Modern Tribe)"
        },
        {
          "title": "Plum Ski-ters Water Ski Show",
          "url": "https://sayner-starlake-cloverland.org/event/plum-ski-ters-water-ski-show-2/2025-08-30/",
          "source": "Sayner\u2013Star Lake\u2013Cloverland Chamber (Modern Tribe)"
        }
      ]
    },
    {
      "name": "Manitowish Waters Chamber (Modern Tribe)",
      "url": "https://manitowishwaters.org/events/?eventDisplay=list",
      "parsed": 0,
      "samples": []
    }
  ]
}