[
  {
    "title": "Pet Blessing at Pioneer Lake Lutheran Church",
    "start": "2025-08-24T00:00:00-05:00",
    "end": "2025-08-24T01:00:00-05:00",
    "location": "Pioneer Lake Lutheran Church 3697 E. Pioneer Church Road, Conover, WI",
    "url": "https://eagleriver.org/events/pioneer-lake-lutheran-church-host-a-pet-blessing/",
    "source": "Eagle River Chamber (Modern Tribe)",
    "all_day": false
  },
  {
    "title": "Free Live Music at Pirates Hideaway",
    "start": "2025-08-24T00:00:00-05:00",
    "end": "2025-08-24T01:00:00-05:00",
    "location": "Pirates Hideaway 1998 US-45, Eagle River, Wisconsin",
    "url": "https://eagleriver.org/events/free-live-music-at-pirates-hideaway-4/2025-08-24/",
    "source": "Eagle River Chamber (Modern Tribe)",
    "all_day": false
  },
  {
    "title": "School Walking Hours at NPHS",
    "start": "2025-08-25T00:00:00-05:00",
    "end": "2025-08-25T01:00:00-05:00",
    "location": "Northland Pines High School 1800 Pleasure Island Road, Eagle River, Wisconsin",
    "url": "https://eagleriver.org/events/school-walking-hours-at-nphs/2025-08-25/",
    "source": "Eagle River Chamber (Modern Tribe)",
    "all_day": false
  },
  {
    "title": "Summer Day Camp at Old Paths Christian Ministries",
    "start": "2025-08-25T00:00:00-05:00",
    "end": "2025-08-25T01:00:00-05:00",
    "location": "Old Paths Christian Ministries",
    "url": "https://eagleriver.org/events/summer-day-camp/2025-08-25/",
    "source": "Eagle River Chamber (Modern Tribe)",
    "all_day": false
  },
  {
    "title": "Summer Arts Venture at LOLA",
    "start": "2025-08-25T00:00:00-05:00",
    "end": "2025-08-25T01:00:00-05:00",
    "location": "LOLA - Land O'Lakes Art Center 4262 Cty Hwy B, Land O'Lakes, WI, United States",
    "url": "https://eagleriver.org/events/summer-arts-venture-at-lola/2025-08-25/",
    "source": "Eagle River Chamber (Modern Tribe)",
    "all_day": false
  },
  {
    "title": "School Walking Hours at NPHS",
    "start": "2025-08-25T00:00:00-05:00",
    "end": "2025-08-25T01:00:00-05:00",
    "location": "Northland Pines High School 1800 Pleasure Island Road, Eagle River, Wisconsin",
    "url": "https://eagleriver.org/events/school-walking-hours-at-nphs-2/2025-08-25/",
    "source": "Eagle River Chamber (Modern Tribe)",
    "all_day": false
  },
  {
    "title": "Ukulele Practice/ Jam Session",
    "start": "2025-08-25T00:00:00-05:00",
    "end": "2025-08-25T01:00:00-05:00",
    "location": "Walter E. Olson Memorial Library 203 North Main Street, Eagle River, Wisconsin",
    "url": "https://eagleriver.org/events/ukulele-practice-jam-session/2025-08-25/",
    "source": "Eagle River Chamber (Modern Tribe)",
    "all_day": false
  },
  {
    "title": "Hatha Yoga Monday Nights at The Warehouse Community Art Center",
    "start": "2025-08-25T00:00:00-05:00",
    "end": "2025-08-25T01:00:00-05:00",
    "location": "The Warehouse Art Center 107 South Railroad Street, Eagle River, Wisconsin",
    "url": "https://eagleriver.org/events/hatha-yoga-monday-nights-at-the-warehouse-community-art-center/2025-08-25/",
    "source": "Eagle River Chamber (Modern Tribe)",
    "all_day": false
  },
  {
    "title": "Summer Day Camp at Old Paths Christian Ministries",
    "start": "2025-08-26T00:00:00-05:00",
    "end": "2025-08-26T01:00:00-05:00",
    "location": "Old Paths Christian Ministries",
    "url": "https://eagleriver.org/events/summer-day-camp/2025-08-26/",
    "source": "Eagle River Chamber (Modern Tribe)",
    "all_day": false
  }
]